Cohesion/__init__.py
Cohesion/cohesionFormula.py
Cohesion/mainPipeline.py
Cohesion/relatedFunctions.py
Cohesion/utils.py
Cohesion/zeroShotClassifier.py
cohesion_measurement-0.1.dist-info/METADATA
cohesion_measurement-0.1.dist-info/WHEEL
cohesion_measurement-0.1.dist-info/top_level.txt
cohesion_measurement-0.1.dist-info/RECORD
