Metadata-Version: 2.1
Name: cohesion-measurement
Version: 0.1
Home-page: https://github.com/TomNachman/Cohesion
Author: Tom,Eden,Asaf
Author-email: nachmant@post.bgu.ac.il
License: MIT
Keywords: cohesion,coherence
Requires-Dist: pandas
Requires-Dist: nltk
Requires-Dist: scikit-learn
Requires-Dist: numpy
Requires-Dist: transformers
Requires-Dist: setuptools
Requires-Dist: scipy
Requires-Dist: gensim
